{
  "benchmark_info": {
    "model_id": "FacebookAI/xlm-roberta-base",
    "task": "fill-mask",
    "device": "gpu",
    "precision": "auto",
    "iterations": 100,
    "warmup": 10,
    "batch_size": 1,
    "timestamp": "2026-05-09T17:25:36.847696+00:00"
  },
  "model_info": {
    "input_names": [
      "input_ids",
      "attention_mask"
    ],
    "input_shapes": [
      [
        1,
        512
      ],
      [
        1,
        512
      ]
    ],
    "input_types": [
      "int32",
      "int32"
    ],
    "output_names": [
      "logits"
    ],
    "output_shapes": [
      [
        1,
        512,
        250002
      ]
    ]
  },
  "latency_ms": {
    "mean": 241.65,
    "min": 232.274,
    "max": 258.325,
    "p50": 241.554,
    "p90": 247.294,
    "p95": 248.749,
    "p99": 258.325,
    "std": 4.085,
    "warmup_mean": 243.725
  },
  "throughput": {
    "samples_per_sec": 4.14,
    "batches_per_sec": 4.14
  },
  "raw_samples_ms": [
    235.911,
    241.551,
    241.554,
    242.731,
    236.168,
    240.663,
    244.232,
    239.705,
    237.617,
    243.382,
    243.158,
    243.623,
    235.519,
    242.517,
    237.825,
    241.308,
    235.248,
    241.795,
    240.452,
    242.673,
    235.898,
    237.472,
    239.94,
    247.594,
    236.142,
    241.778,
    236.698,
    240.461,
    243.644,
    241.256,
    232.274,
    241.216,
    246.189,
    239.364,
    239.393,
    237.51,
    248.954,
    241.805,
    238.573,
    242.195,
    246.661,
    239.63,
    239.781,
    242.297,
    248.41,
    243.005,
    243.077,
    242.084,
    247.281,
    242.034,
    242.729,
    242.568,
    243.223,
    239.741,
    236.099,
    237.397,
    249.104,
    241.245,
    236.875,
    241.637,
    258.325,
    241.806,
    241.437,
    242.56,
    243.782,
    243.496,
    239.928,
    241.368,
    247.294,
    241.196,
    236.342,
    240.271,
    248.749,
    241.823,
    241.927,
    242.161,
    247.396,
    241.645,
    238.848,
    238.112,
    258.206,
    238.714,
    240.694,
    239.613,
    242.24,
    240.977,
    240.552,
    241.476,
    246.653,
    242.031,
    243.533,
    240.143,
    244.995,
    237.237,
    242.431,
    238.047,
    247.777,
    238.381,
    241.96,
    240.001
  ]
}