{
  "benchmark_info": {
    "model_id": "BAAI/bge-large-en-v1.5",
    "task": "sentence-similarity",
    "device": "gpu",
    "precision": "auto",
    "iterations": 100,
    "warmup": 10,
    "batch_size": 1,
    "timestamp": "2026-05-17T05:20:36.734228+00:00"
  },
  "model_info": {
    "input_names": [
      "input_ids",
      "attention_mask",
      "token_type_ids"
    ],
    "input_shapes": [
      [
        1,
        512
      ],
      [
        1,
        512
      ],
      [
        1,
        512
      ]
    ],
    "input_types": [
      "int32",
      "int32",
      "int32"
    ],
    "output_names": [
      "last_hidden_state",
      "2625"
    ],
    "output_shapes": [
      [
        1,
        512,
        1024
      ],
      [
        1,
        1024
      ]
    ]
  },
  "latency_ms": {
    "mean": 53.962,
    "min": 35.656,
    "max": 59.333,
    "p50": 53.887,
    "p90": 56.851,
    "p95": 57.505,
    "p99": 59.333,
    "std": 3.27,
    "warmup_mean": 51.999
  },
  "throughput": {
    "samples_per_sec": 18.53,
    "batches_per_sec": 18.53
  },
  "raw_samples_ms": [
    57.01,
    56.624,
    56.51,
    56.347,
    56.513,
    56.341,
    56.625,
    56.812,
    56.513,
    56.503,
    56.688,
    56.825,
    57.682,
    56.532,
    56.418,
    56.762,
    56.283,
    56.832,
    56.657,
    56.492,
    56.822,
    56.934,
    56.954,
    57.585,
    57.505,
    56.643,
    56.566,
    56.358,
    56.349,
    56.588,
    56.709,
    56.288,
    56.644,
    56.163,
    56.851,
    56.676,
    56.392,
    56.837,
    56.118,
    56.223,
    56.154,
    56.562,
    59.333,
    58.282,
    56.812,
    56.85,
    56.749,
    56.877,
    56.418,
    46.848,
    35.656,
    49.767,
    51.99,
    51.632,
    52.409,
    51.863,
    52.054,
    50.276,
    50.176,
    51.856,
    51.905,
    52.065,
    51.689,
    53.507,
    52.27,
    52.141,
    52.117,
    50.783,
    50.633,
    51.822,
    50.981,
    51.414,
    51.264,
    53.306,
    52.998,
    52.073,
    51.306,
    51.443,
    51.881,
    51.318,
    52.565,
    51.323,
    52.299,
    51.551,
    50.177,
    52.802,
    51.039,
    51.629,
    51.983,
    52.881,
    50.97,
    51.711,
    50.823,
    50.759,
    50.271,
    52.343,
    53.887,
    50.093,
    52.699,
    52.699
  ]
}