{
  "benchmark_info": {
    "model_id": "laion/CLIP-ViT-B-32-laion2B-s34B-b79K",
    "task": "feature-extraction",
    "device": "gpu",
    "precision": "auto",
    "iterations": 100,
    "warmup": 10,
    "batch_size": 1,
    "timestamp": "2026-05-09T21:32:21.054419+00:00"
  },
  "model_info": {
    "input_names": [
      "input_ids",
      "attention_mask"
    ],
    "input_shapes": [
      [
        1,
        77
      ],
      [
        1,
        77
      ]
    ],
    "input_types": [
      "int32",
      "int32"
    ],
    "output_names": [
      "text_embeds",
      "last_hidden_state"
    ],
    "output_shapes": [
      [
        1,
        512
      ],
      [
        1,
        77,
        512
      ]
    ]
  },
  "latency_ms": {
    "mean": 1.65,
    "min": 1.552,
    "max": 2.579,
    "p50": 1.6,
    "p90": 1.752,
    "p95": 1.989,
    "p99": 2.579,
    "std": 0.158,
    "warmup_mean": 1.956
  },
  "throughput": {
    "samples_per_sec": 606.11,
    "batches_per_sec": 606.11
  },
  "raw_samples_ms": [
    1.672,
    1.758,
    1.659,
    1.611,
    1.584,
    1.591,
    1.584,
    1.581,
    1.569,
    1.566,
    1.752,
    1.826,
    1.667,
    1.615,
    1.573,
    1.568,
    1.576,
    1.579,
    1.588,
    1.712,
    1.679,
    1.651,
    1.594,
    1.552,
    1.608,
    1.582,
    1.597,
    1.592,
    1.592,
    1.854,
    2.579,
    1.719,
    1.658,
    1.61,
    1.595,
    1.565,
    1.572,
    1.558,
    1.996,
    2.099,
    1.7,
    1.989,
    1.705,
    1.735,
    1.606,
    1.614,
    1.596,
    1.621,
    1.605,
    1.69,
    1.599,
    1.585,
    1.595,
    1.64,
    1.595,
    1.595,
    1.603,
    1.592,
    1.565,
    1.597,
    1.6,
    1.624,
    1.595,
    1.587,
    1.591,
    1.582,
    1.617,
    1.61,
    1.596,
    1.586,
    1.672,
    1.621,
    1.591,
    1.589,
    1.605,
    1.618,
    1.605,
    1.591,
    1.588,
    1.617,
    1.59,
    1.593,
    1.608,
    1.579,
    1.582,
    1.845,
    2.54,
    1.625,
    1.593,
    1.607,
    1.593,
    1.6,
    1.605,
    1.66,
    1.618,
    1.616,
    1.583,
    1.588,
    1.583,
    1.583
  ]
}