{
  "benchmark_info": {
    "model_id": "facebook/dinov2-large",
    "task": "image-feature-extraction",
    "device": "npu",
    "ep": "VitisAIExecutionProvider",
    "precision": "auto",
    "iterations": 100,
    "warmup": 10,
    "batch_size": 1,
    "timestamp": "2026-05-27T15:14:06.739994+00:00"
  },
  "model_info": {
    "input_names": [
      "pixel_values"
    ],
    "input_shapes": [
      [
        1,
        3,
        224,
        224
      ]
    ],
    "input_types": [
      "float32"
    ],
    "output_names": [
      "last_hidden_state",
      "2750"
    ],
    "output_shapes": [
      [
        1,
        257,
        1024
      ],
      [
        1,
        1024
      ]
    ]
  },
  "latency_ms": {
    "mean": 145.968,
    "min": 142.737,
    "max": 158.374,
    "p50": 144.925,
    "p90": 149.648,
    "p95": 154.141,
    "p99": 158.374,
    "std": 3.078,
    "warmup_mean": 146.84
  },
  "throughput": {
    "samples_per_sec": 6.85,
    "batches_per_sec": 6.85
  },
  "raw_samples_ms": [
    144.613,
    144.956,
    145.509,
    144.979,
    154.114,
    144.66,
    145.112,
    143.742,
    144.002,
    146.025,
    154.612,
    150.778,
    144.756,
    144.119,
    143.628,
    143.043,
    145.644,
    144.431,
    147.198,
    143.97,
    155.658,
    158.374,
    143.352,
    143.589,
    143.685,
    144.314,
    145.502,
    143.367,
    144.212,
    145.335,
    148.116,
    144.857,
    143.751,
    147.525,
    145.639,
    145.394,
    145.036,
    145.818,
    144.299,
    144.825,
    144.925,
    154.141,
    143.793,
    144.459,
    144.321,
    144.776,
    144.198,
    145.617,
    144.121,
    146.727,
    145.955,
    143.86,
    144.917,
    144.913,
    149.648,
    144.356,
    148.138,
    147.429,
    147.864,
    144.034,
    148.023,
    145.41,
    146.165,
    143.74,
    143.737,
    147.656,
    144.277,
    144.331,
    144.835,
    144.467,
    143.942,
    143.696,
    145.81,
    144.153,
    143.73,
    158.125,
    144.715,
    143.91,
    148.069,
    153.503,
    144.42,
    142.737,
    144.172,
    144.235,
    144.824,
    145.195,
    150.948,
    147.161,
    144.905,
    143.991,
    146.631,
    145.367,
    145.596,
    145.205,
    145.01,
    146.932,
    145.257,
    147.555,
    146.011,
    147.662
  ]
}