{
  "benchmark_info": {
    "model_id": "google/siglip-base-patch16-224",
    "task": "feature-extraction",
    "device": "npu",
    "precision": "auto",
    "iterations": 100,
    "warmup": 10,
    "batch_size": 1,
    "timestamp": "2026-05-08T18:25:57.525638+00:00"
  },
  "model_info": {
    "input_names": [
      "input_ids"
    ],
    "input_shapes": [
      [
        1,
        64
      ]
    ],
    "input_types": [
      "int32"
    ],
    "output_names": [
      "last_hidden_state",
      "pooler_output"
    ],
    "output_shapes": [
      [
        1,
        64,
        768
      ],
      [
        1,
        768
      ]
    ]
  },
  "latency_ms": {
    "mean": 5.791,
    "min": 5.057,
    "max": 8.206,
    "p50": 5.643,
    "p90": 6.349,
    "p95": 7.294,
    "p99": 8.206,
    "std": 0.569,
    "warmup_mean": 13.636
  },
  "throughput": {
    "samples_per_sec": 172.69,
    "batches_per_sec": 172.69
  },
  "raw_samples_ms": [
    8.206,
    8.108,
    7.715,
    7.61,
    7.294,
    7.053,
    7.234,
    6.569,
    6.349,
    6.22,
    6.165,
    5.992,
    5.888,
    5.879,
    5.884,
    5.696,
    5.749,
    5.909,
    5.815,
    5.857,
    5.812,
    5.871,
    5.76,
    5.372,
    5.314,
    5.356,
    5.337,
    5.302,
    5.346,
    5.755,
    5.644,
    5.405,
    5.605,
    5.636,
    6.578,
    5.495,
    5.56,
    5.569,
    5.643,
    5.597,
    5.91,
    6.069,
    5.758,
    5.755,
    5.609,
    5.672,
    5.655,
    5.649,
    5.608,
    5.655,
    5.584,
    5.713,
    5.704,
    5.893,
    5.785,
    5.643,
    5.73,
    5.65,
    5.638,
    5.644,
    5.538,
    5.441,
    5.497,
    5.524,
    5.527,
    6.067,
    6.199,
    5.436,
    5.34,
    5.261,
    5.057,
    5.392,
    5.503,
    5.384,
    5.442,
    5.641,
    5.483,
    5.517,
    5.731,
    5.761,
    5.57,
    5.919,
    5.58,
    5.493,
    5.467,
    5.426,
    5.43,
    5.45,
    5.318,
    5.421,
    5.307,
    5.625,
    5.656,
    5.629,
    5.643,
    5.603,
    5.588,
    5.675,
    5.552,
    5.521
  ]
}