{
  "benchmark_info": {
    "model_id": "dslim/bert-base-NER",
    "task": "token-classification",
    "device": "gpu",
    "precision": "auto",
    "iterations": 100,
    "warmup": 10,
    "batch_size": 1,
    "timestamp": "2026-05-18T19:17:39.750425+00:00"
  },
  "model_info": {
    "input_names": [
      "input_ids",
      "attention_mask",
      "token_type_ids"
    ],
    "input_shapes": [
      [
        1,
        512
      ],
      [
        1,
        512
      ],
      [
        1,
        512
      ]
    ],
    "input_types": [
      "int32",
      "int32",
      "int32"
    ],
    "output_names": [
      "logits"
    ],
    "output_shapes": [
      [
        1,
        512,
        9
      ]
    ]
  },
  "latency_ms": {
    "mean": 183.278,
    "min": 179.191,
    "max": 205.249,
    "p50": 182.953,
    "p90": 184.987,
    "p95": 186.901,
    "p99": 205.249,
    "std": 2.743,
    "warmup_mean": 186.237
  },
  "throughput": {
    "samples_per_sec": 5.46,
    "batches_per_sec": 5.46
  },
  "raw_samples_ms": [
    182.838,
    184.581,
    182.931,
    182.232,
    182.817,
    181.454,
    179.191,
    182.58,
    183.335,
    182.032,
    185.667,
    181.366,
    182.712,
    183.412,
    183.222,
    181.713,
    183.063,
    183.462,
    182.266,
    183.349,
    183.391,
    205.249,
    183.96,
    182.505,
    181.153,
    181.616,
    184.613,
    183.272,
    182.953,
    183.457,
    183.178,
    182.726,
    179.78,
    183.74,
    180.905,
    182.669,
    183.978,
    181.593,
    183.078,
    182.773,
    183.585,
    184.146,
    183.545,
    181.458,
    182.435,
    182.81,
    182.129,
    183.79,
    185.274,
    184.195,
    180.343,
    187.453,
    183.257,
    181.263,
    182.723,
    182.492,
    179.963,
    184.296,
    181.544,
    182.693,
    183.241,
    183.248,
    183.218,
    183.8,
    182.703,
    184.712,
    181.206,
    182.158,
    182.721,
    182.332,
    183.663,
    183.15,
    182.191,
    184.09,
    183.695,
    183.237,
    189.717,
    182.341,
    182.281,
    189.4,
    183.737,
    182.595,
    186.901,
    182.225,
    184.987,
    182.502,
    183.052,
    185.567,
    182.117,
    183.596,
    182.391,
    182.583,
    183.211,
    181.007,
    183.505,
    183.152,
    182.034,
    186.045,
    182.604,
    180.712
  ]
}