{
  "benchmark_info": {
    "model_id": "FacebookAI/roberta-large",
    "task": "fill-mask",
    "device": "cpu",
    "precision": "auto",
    "iterations": 100,
    "warmup": 10,
    "batch_size": 1,
    "timestamp": "2026-05-11T11:40:38.993676+00:00"
  },
  "model_info": {
    "input_names": [
      "input_ids",
      "attention_mask"
    ],
    "input_shapes": [
      [
        1,
        512
      ],
      [
        1,
        512
      ]
    ],
    "input_types": [
      "int32",
      "int32"
    ],
    "output_names": [
      "logits"
    ],
    "output_shapes": [
      [
        1,
        512,
        50265
      ]
    ]
  },
  "latency_ms": {
    "mean": 2292.842,
    "min": 1959.534,
    "max": 3298.148,
    "p50": 2229.751,
    "p90": 2620.266,
    "p95": 2873.812,
    "p99": 3298.148,
    "std": 259.836,
    "warmup_mean": 2258.755
  },
  "throughput": {
    "samples_per_sec": 0.44,
    "batches_per_sec": 0.44
  },
  "raw_samples_ms": [
    2441.365,
    2295.047,
    2340.285,
    2117.062,
    2149.029,
    2023.394,
    2426.446,
    2182.476,
    2404.296,
    2108.591,
    2749.691,
    2504.699,
    2383.67,
    3298.148,
    2489.822,
    2661.312,
    2515.082,
    2016.172,
    2137.279,
    2264.193,
    2257.123,
    2016.797,
    2007.929,
    2620.266,
    2403.765,
    2382.376,
    2336.01,
    2013.323,
    2104.536,
    2166.041,
    2134.08,
    2951.635,
    2293.599,
    2873.812,
    2778.338,
    2101.9,
    2030.151,
    2228.052,
    2111.437,
    2123.343,
    2162.014,
    1997.818,
    2128.213,
    2140.056,
    2152.231,
    2096.273,
    1959.534,
    2227.303,
    2182.063,
    2166.865,
    2249.138,
    2366.696,
    3247.448,
    2308.979,
    3204.101,
    2537.632,
    2415.648,
    2155.479,
    2302.949,
    2225.268,
    2229.751,
    2322.983,
    2331.544,
    2136.181,
    2329.815,
    2063.264,
    2046.262,
    2359.593,
    2214.796,
    2486.13,
    2215.436,
    2153.731,
    2693.61,
    2119.59,
    2029.726,
    2325.859,
    2221.769,
    2356.895,
    2240.448,
    2121.999,
    2055.289,
    2517.93,
    2018.797,
    2119.968,
    2281.067,
    2089.962,
    2198.287,
    2090.96,
    2194.091,
    2250.455,
    2373.638,
    2284.268,
    2148.734,
    2600.392,
    2261.233,
    2096.485,
    1986.377,
    2385.102,
    2335.483,
    2328.051
  ]
}