{
  "benchmark_info": {
    "model_id": "cross-encoder/nli-deberta-v3-small",
    "task": "zero-shot-classification",
    "device": "cpu",
    "precision": "auto",
    "iterations": 100,
    "warmup": 10,
    "batch_size": 1,
    "timestamp": "2026-05-11T03:48:28.494395+00:00"
  },
  "model_info": {
    "input_names": [
      "input_ids",
      "attention_mask"
    ],
    "input_shapes": [
      [
        1,
        512
      ],
      [
        1,
        512
      ]
    ],
    "input_types": [
      "int32",
      "int32"
    ],
    "output_names": [
      "logits"
    ],
    "output_shapes": [
      [
        1,
        3
      ]
    ]
  },
  "latency_ms": {
    "mean": 163.52,
    "min": 157.938,
    "max": 169.512,
    "p50": 163.024,
    "p90": 166.258,
    "p95": 168.881,
    "p99": 169.512,
    "std": 1.966,
    "warmup_mean": 168.584
  },
  "throughput": {
    "samples_per_sec": 6.12,
    "batches_per_sec": 6.12
  },
  "raw_samples_ms": [
    165.559,
    165.156,
    164.328,
    162.231,
    162.204,
    163.361,
    163.77,
    162.555,
    161.7,
    164.552,
    162.266,
    162.773,
    163.998,
    163.774,
    163.753,
    163.173,
    163.259,
    163.557,
    162.185,
    162.745,
    164.32,
    166.258,
    162.538,
    162.075,
    167.59,
    162.91,
    160.772,
    169.123,
    168.881,
    165.029,
    162.614,
    163.037,
    162.712,
    161.142,
    164.956,
    163.425,
    162.419,
    163.024,
    162.025,
    163.54,
    161.954,
    163.052,
    166.729,
    163.052,
    169.512,
    163.261,
    161.55,
    166.598,
    162.634,
    163.992,
    162.926,
    162.977,
    163.796,
    163.202,
    163.685,
    164.996,
    162.329,
    164.347,
    162.075,
    161.931,
    161.846,
    165.401,
    160.978,
    164.993,
    162.438,
    162.758,
    162.921,
    162.778,
    163.087,
    165.892,
    162.943,
    162.643,
    162.833,
    162.001,
    163.144,
    162.956,
    163.399,
    161.827,
    162.594,
    157.938,
    159.926,
    162.757,
    163.736,
    162.139,
    163.771,
    165.728,
    169.346,
    165.805,
    162.877,
    162.105,
    162.373,
    166.844,
    169.273,
    162.09,
    163.822,
    162.954,
    162.838,
    161.033,
    164.535,
    162.822
  ]
}