{
  "benchmark_info": {
    "model_id": "facebook/dinov2-base",
    "task": "image-feature-extraction",
    "device": "npu",
    "ep": "QNNExecutionProvider",
    "precision": "auto",
    "iterations": 100,
    "warmup": 10,
    "batch_size": 1,
    "timestamp": "2026-05-22T21:32:54.449998+00:00"
  },
  "model_info": {
    "input_names": [
      "pixel_values"
    ],
    "input_shapes": [
      [
        1,
        3,
        224,
        224
      ]
    ],
    "input_types": [
      "float32"
    ],
    "output_names": [
      "last_hidden_state",
      "1430"
    ],
    "output_shapes": [
      [
        1,
        257,
        768
      ],
      [
        1,
        768
      ]
    ]
  },
  "latency_ms": {
    "mean": 14.105,
    "min": 9.665,
    "max": 22.98,
    "p50": 14.366,
    "p90": 18.361,
    "p95": 18.751,
    "p99": 22.98,
    "std": 3.107,
    "warmup_mean": 14.138
  },
  "throughput": {
    "samples_per_sec": 70.89,
    "batches_per_sec": 70.89
  },
  "raw_samples_ms": [
    17.358,
    15.741,
    15.484,
    15.192,
    11.175,
    16.914,
    11.176,
    16.748,
    16.469,
    15.652,
    17.626,
    14.197,
    11.568,
    15.389,
    16.116,
    15.547,
    17.04,
    17.592,
    15.265,
    15.93,
    18.049,
    14.551,
    14.556,
    10.74,
    10.552,
    10.94,
    10.336,
    10.338,
    12.166,
    10.644,
    10.654,
    15.429,
    13.038,
    18.584,
    16.355,
    18.568,
    12.644,
    17.512,
    12.497,
    10.608,
    10.717,
    13.159,
    17.833,
    14.723,
    18.361,
    15.247,
    17.713,
    14.288,
    18.599,
    14.842,
    16.32,
    18.431,
    13.72,
    19.833,
    13.98,
    18.063,
    14.165,
    15.637,
    18.993,
    13.56,
    11.329,
    14.366,
    10.615,
    14.541,
    15.598,
    10.816,
    22.98,
    15.839,
    15.795,
    11.269,
    18.751,
    14.062,
    10.351,
    10.48,
    11.54,
    10.275,
    10.318,
    11.881,
    10.157,
    10.305,
    14.752,
    10.546,
    21.504,
    10.496,
    10.489,
    17.326,
    14.943,
    15.813,
    17.794,
    13.213,
    10.467,
    10.335,
    10.507,
    10.47,
    10.437,
    11.134,
    10.46,
    9.723,
    14.076,
    9.665
  ]
}