{
  "benchmark_info": {
    "model_id": "laion/CLIP-ViT-B-32-laion2B-s34B-b79K",
    "task": "feature-extraction",
    "device": "gpu",
    "ep": "DmlExecutionProvider",
    "precision": "auto",
    "iterations": 100,
    "warmup": 10,
    "batch_size": 1,
    "timestamp": "2026-05-22T12:45:18.125277+00:00"
  },
  "model_info": {
    "input_names": [
      "input_ids",
      "attention_mask"
    ],
    "input_shapes": [
      [
        1,
        77
      ],
      [
        1,
        77
      ]
    ],
    "input_types": [
      "int32",
      "int32"
    ],
    "output_names": [
      "text_embeds",
      "last_hidden_state"
    ],
    "output_shapes": [
      [
        1,
        512
      ],
      [
        1,
        77,
        512
      ]
    ]
  },
  "latency_ms": {
    "mean": 36.501,
    "min": 35.842,
    "max": 37.27,
    "p50": 36.52,
    "p90": 36.745,
    "p95": 36.815,
    "p99": 37.27,
    "std": 0.227,
    "warmup_mean": 37.172
  },
  "throughput": {
    "samples_per_sec": 27.4,
    "batches_per_sec": 27.4
  },
  "raw_samples_ms": [
    36.781,
    36.616,
    36.692,
    36.488,
    36.172,
    36.146,
    36.056,
    36.104,
    36.233,
    36.401,
    36.53,
    36.587,
    36.724,
    36.352,
    36.468,
    36.542,
    36.457,
    36.165,
    36.191,
    36.034,
    36.601,
    36.538,
    36.883,
    36.849,
    37.023,
    36.702,
    36.52,
    36.364,
    36.091,
    36.42,
    36.398,
    36.732,
    36.69,
    36.793,
    36.527,
    36.621,
    36.725,
    36.745,
    36.731,
    36.546,
    36.433,
    36.704,
    36.485,
    36.593,
    36.548,
    36.444,
    36.692,
    36.48,
    37.27,
    36.737,
    36.198,
    36.2,
    36.328,
    36.406,
    36.194,
    36.279,
    36.549,
    36.595,
    36.631,
    36.683,
    36.499,
    36.579,
    36.147,
    36.259,
    36.638,
    36.616,
    36.46,
    36.461,
    36.396,
    36.599,
    36.577,
    36.504,
    36.336,
    36.352,
    36.574,
    36.617,
    36.746,
    36.492,
    36.518,
    36.416,
    36.459,
    36.494,
    36.454,
    36.343,
    36.242,
    36.723,
    36.606,
    36.457,
    36.665,
    36.537,
    36.776,
    36.612,
    36.815,
    36.388,
    35.842,
    36.614,
    36.664,
    36.016,
    36.351,
    36.52
  ]
}