{
  "benchmark_info": {
    "model_id": "lxyuan/distilbert-base-multilingual-cased-sentiments-student",
    "task": "zero-shot-classification",
    "device": "cpu",
    "precision": "auto",
    "iterations": 100,
    "warmup": 10,
    "batch_size": 1,
    "timestamp": "2026-05-11T12:52:26.340990+00:00"
  },
  "model_info": {
    "input_names": [
      "input_ids",
      "attention_mask"
    ],
    "input_shapes": [
      [
        1,
        512
      ],
      [
        1,
        512
      ]
    ],
    "input_types": [
      "int32",
      "int32"
    ],
    "output_names": [
      "logits"
    ],
    "output_shapes": [
      [
        1,
        3
      ]
    ]
  },
  "latency_ms": {
    "mean": 103.032,
    "min": 88.464,
    "max": 109.511,
    "p50": 103.63,
    "p90": 105.522,
    "p95": 106.895,
    "p99": 109.511,
    "std": 3.049,
    "warmup_mean": 108.684
  },
  "throughput": {
    "samples_per_sec": 9.71,
    "batches_per_sec": 9.71
  },
  "raw_samples_ms": [
    109.511,
    103.497,
    105.995,
    104.228,
    104.408,
    105.468,
    101.064,
    104.892,
    102.851,
    104.887,
    103.122,
    104.702,
    102.868,
    102.3,
    104.773,
    104.988,
    102.319,
    104.381,
    103.875,
    103.868,
    101.976,
    104.941,
    103.126,
    106.827,
    104.29,
    102.938,
    104.699,
    103.409,
    103.093,
    104.654,
    103.961,
    104.517,
    103.884,
    100.406,
    107.422,
    103.63,
    105.034,
    106.895,
    101.229,
    104.514,
    103.15,
    101.258,
    102.88,
    103.278,
    105.217,
    103.882,
    105.941,
    103.174,
    101.992,
    103.87,
    103.093,
    105.522,
    100.595,
    104.779,
    103.192,
    98.574,
    94.468,
    94.363,
    102.414,
    98.578,
    104.575,
    103.333,
    102.34,
    101.117,
    93.86,
    92.938,
    88.464,
    98.345,
    100.001,
    104.369,
    103.727,
    103.882,
    104.056,
    100.359,
    105.871,
    102.955,
    103.575,
    103.608,
    103.321,
    99.549,
    103.81,
    103.01,
    102.995,
    101.44,
    103.849,
    103.555,
    105.233,
    104.11,
    107.322,
    104.631,
    100.665,
    104.672,
    103.384,
    101.209,
    105.121,
    105.179,
    103.796,
    101.851,
    107.17,
    104.304
  ]
}