{
  "benchmark_info": {
    "model_id": "w11wo/indonesian-roberta-base-posp-tagger",
    "task": "token-classification",
    "device": "cpu",
    "precision": "auto",
    "iterations": 100,
    "warmup": 10,
    "batch_size": 1,
    "timestamp": "2026-05-17T14:38:34.279746+00:00"
  },
  "model_info": {
    "input_names": [
      "input_ids",
      "attention_mask"
    ],
    "input_shapes": [
      [
        1,
        512
      ],
      [
        1,
        512
      ]
    ],
    "input_types": [
      "int32",
      "int32"
    ],
    "output_names": [
      "logits"
    ],
    "output_shapes": [
      [
        1,
        512,
        26
      ]
    ]
  },
  "latency_ms": {
    "mean": 414.204,
    "min": 376.162,
    "max": 641.391,
    "p50": 400.871,
    "p90": 461.742,
    "p95": 511.387,
    "p99": 641.391,
    "std": 41.473,
    "warmup_mean": 455.456
  },
  "throughput": {
    "samples_per_sec": 2.41,
    "batches_per_sec": 2.41
  },
  "raw_samples_ms": [
    444.558,
    450.304,
    535.371,
    459.159,
    448.432,
    417.867,
    418.225,
    409.797,
    396.36,
    400.783,
    423.528,
    390.982,
    392.027,
    401.281,
    395.491,
    641.391,
    529.206,
    413.509,
    430.624,
    430.684,
    427.921,
    407.089,
    400.871,
    393.405,
    529.852,
    426.484,
    402.813,
    396.945,
    410.033,
    421.908,
    393.321,
    417.905,
    413.963,
    395.063,
    397.32,
    386.951,
    389.201,
    376.162,
    395.024,
    401.283,
    385.848,
    381.971,
    387.429,
    401.95,
    434.497,
    449.178,
    431.444,
    435.135,
    433.667,
    417.346,
    489.85,
    463.733,
    430.483,
    511.387,
    485.156,
    458.713,
    420.786,
    406.72,
    401.067,
    390.163,
    390.917,
    379.998,
    389.694,
    392.645,
    381.091,
    388.616,
    382.423,
    377.723,
    384.895,
    390.786,
    379.471,
    377.547,
    428.202,
    483.115,
    461.742,
    420.324,
    400.902,
    400.048,
    423.282,
    398.673,
    392.23,
    392.27,
    399.243,
    383.423,
    380.951,
    380.995,
    377.714,
    381.306,
    390.582,
    389.429,
    386.248,
    391.334,
    401.467,
    380.243,
    391.233,
    387.768,
    382.143,
    380.333,
    382.295,
    407.444
  ]
}