{
  "benchmark_info": {
    "model_id": "Intel/bert-base-uncased-mrpc",
    "task": "feature-extraction",
    "device": "gpu",
    "ep": "QNNExecutionProvider",
    "precision": "auto",
    "iterations": 100,
    "warmup": 10,
    "batch_size": 1,
    "timestamp": "2026-05-26T02:08:36.140993+00:00"
  },
  "model_info": {
    "input_names": [
      "input_ids",
      "attention_mask",
      "token_type_ids"
    ],
    "input_shapes": [
      [
        1,
        512
      ],
      [
        1,
        512
      ],
      [
        1,
        512
      ]
    ],
    "input_types": [
      "int32",
      "int32",
      "int32"
    ],
    "output_names": [
      "last_hidden_state"
    ],
    "output_shapes": [
      [
        1,
        512,
        768
      ]
    ]
  },
  "latency_ms": {
    "mean": 108.128,
    "min": 85.016,
    "max": 131.195,
    "p50": 112.212,
    "p90": 124.587,
    "p95": 127.826,
    "p99": 131.195,
    "std": 13.89,
    "warmup_mean": 112.194
  },
  "throughput": {
    "samples_per_sec": 9.25,
    "batches_per_sec": 9.25
  },
  "raw_samples_ms": [
    111.789,
    120.821,
    112.664,
    111.631,
    112.426,
    113.321,
    119.277,
    125.013,
    126.386,
    127.826,
    127.16,
    85.137,
    114.652,
    122.418,
    119.372,
    117.085,
    121.143,
    122.31,
    121.49,
    121.957,
    131.195,
    101.393,
    110.632,
    110.447,
    129.078,
    101.144,
    120.665,
    120.407,
    124.587,
    120.158,
    124.552,
    108.676,
    89.106,
    88.359,
    89.458,
    90.036,
    95.391,
    91.139,
    95.095,
    90.062,
    87.333,
    86.861,
    86.244,
    93.406,
    116.56,
    88.545,
    85.874,
    85.191,
    106.806,
    120.371,
    103.014,
    85.558,
    88.463,
    90.471,
    96.599,
    102.224,
    100.685,
    87.884,
    85.824,
    87.584,
    92.965,
    96.611,
    90.824,
    85.721,
    85.543,
    85.016,
    108.108,
    96.064,
    112.212,
    130.805,
    117.392,
    118.824,
    126.877,
    122.674,
    107.57,
    113.056,
    111.589,
    112.214,
    112.916,
    114.449,
    112.525,
    111.957,
    114.15,
    117.532,
    123.276,
    128.27,
    121.64,
    116.7,
    114.999,
    112.154,
    113.945,
    111.114,
    113.532,
    115.846,
    98.405,
    120.097,
    117.28,
    111.924,
    113.056,
    112.018
  ]
}