{
  "benchmark_info": {
    "model_id": "google-bert/bert-base-multilingual-cased",
    "task": "feature-extraction",
    "device": "cpu",
    "precision": "auto",
    "iterations": 100,
    "warmup": 10,
    "batch_size": 1,
    "timestamp": "2026-05-11T10:05:46.382318+00:00"
  },
  "model_info": {
    "input_names": [
      "input_ids",
      "attention_mask",
      "token_type_ids"
    ],
    "input_shapes": [
      [
        1,
        512
      ],
      [
        1,
        512
      ],
      [
        1,
        512
      ]
    ],
    "input_types": [
      "int32",
      "int32",
      "int32"
    ],
    "output_names": [
      "last_hidden_state"
    ],
    "output_shapes": [
      [
        1,
        512,
        768
      ]
    ]
  },
  "latency_ms": {
    "mean": 205.805,
    "min": 186.554,
    "max": 216.121,
    "p50": 207.065,
    "p90": 210.331,
    "p95": 211.159,
    "p99": 216.121,
    "std": 5.45,
    "warmup_mean": 211.103
  },
  "throughput": {
    "samples_per_sec": 4.86,
    "batches_per_sec": 4.86
  },
  "raw_samples_ms": [
    207.13,
    210.852,
    203.864,
    208.259,
    210.01,
    205.278,
    208.46,
    206.252,
    208.802,
    208.699,
    203.553,
    199.286,
    194.455,
    195.626,
    208.507,
    207.302,
    205.976,
    207.877,
    210.507,
    209.743,
    210.539,
    203.59,
    209.243,
    208.771,
    206.608,
    208.491,
    204.318,
    206.566,
    195.119,
    187.456,
    186.554,
    208.538,
    206.425,
    207.367,
    210.168,
    208.676,
    207.636,
    210.098,
    216.121,
    210.196,
    210.57,
    213.013,
    205.342,
    205.644,
    211.159,
    201.622,
    204.734,
    209.985,
    204.303,
    213.498,
    209.84,
    208.415,
    208.657,
    205.74,
    208.124,
    207.428,
    198.971,
    206.899,
    212.162,
    204.359,
    208.221,
    195.385,
    187.571,
    203.168,
    208.951,
    206.15,
    209.534,
    210.261,
    205.45,
    207.683,
    205.248,
    207.065,
    205.577,
    209.729,
    206.337,
    208.29,
    203.181,
    203.57,
    193.764,
    191.041,
    191.584,
    206.114,
    207.473,
    208.268,
    205.142,
    205.856,
    206.974,
    206.565,
    209.346,
    205.635,
    207.128,
    206.031,
    206.173,
    204.62,
    205.233,
    205.343,
    206.624,
    207.865,
    210.331,
    208.633
  ]
}