{
  "benchmark_info": {
    "model_id": "google-bert/bert-base-multilingual-cased",
    "task": "feature-extraction",
    "device": "npu",
    "precision": "auto",
    "iterations": 100,
    "warmup": 10,
    "batch_size": 1,
    "timestamp": "2026-04-28T11:53:02.793099+00:00"
  },
  "model_info": {
    "input_names": [
      "input_ids",
      "attention_mask",
      "token_type_ids"
    ],
    "input_shapes": [
      [
        1,
        512
      ],
      [
        1,
        512
      ],
      [
        1,
        512
      ]
    ],
    "input_types": [
      "int32",
      "int32",
      "int32"
    ],
    "output_names": [
      "last_hidden_state"
    ],
    "output_shapes": [
      [
        1,
        512,
        768
      ]
    ]
  },
  "latency_ms": {
    "mean": 137.701,
    "min": 127.135,
    "max": 144.064,
    "p50": 138.393,
    "p90": 141.362,
    "p95": 142.061,
    "p99": 144.064,
    "std": 3.098,
    "warmup_mean": 133.295
  },
  "throughput": {
    "samples_per_sec": 7.26,
    "batches_per_sec": 7.26
  },
  "raw_samples_ms": [
    138.722,
    140.707,
    139.414,
    139.454,
    136.11,
    137.887,
    141.705,
    139.381,
    137.621,
    140.267,
    135.343,
    137.21,
    133.426,
    135.135,
    135.68,
    142.155,
    140.799,
    138.501,
    134.225,
    142.047,
    138.705,
    131.82,
    131.729,
    138.393,
    140.556,
    142.864,
    136.028,
    140.046,
    138.372,
    142.061,
    140.066,
    139.714,
    140.53,
    136.273,
    138.818,
    138.774,
    139.042,
    138.765,
    143.159,
    139.11,
    136.618,
    134.014,
    132.173,
    134.987,
    140.382,
    141.365,
    137.005,
    137.181,
    138.859,
    137.363,
    140.441,
    141.034,
    135.522,
    137.168,
    138.65,
    141.362,
    138.666,
    139.676,
    137.468,
    138.086,
    131.828,
    136.093,
    132.486,
    139.76,
    133.904,
    135.86,
    138.851,
    137.234,
    144.064,
    139.415,
    141.351,
    133.324,
    127.135,
    130.547,
    131.65,
    135.657,
    134.678,
    135.608,
    132.375,
    137.89,
    134.994,
    138.829,
    138.717,
    138.003,
    138.891,
    135.734,
    139.779,
    141.132,
    135.7,
    138.031,
    139.732,
    140.794,
    139.911,
    141.885,
    139.056,
    136.716,
    137.116,
    135.588,
    133.011,
    138.143
  ]
}