{
    "benchmark_info":  {
                           "model_id":  "dslim/bert-base-NER",
                           "task":  "token-classification",
                           "device":  "cpu",
                           "ep":  "OpenVINOExecutionProvider",
                           "precision":  "",
                           "iterations":  10,
                           "warmup":  2,
                           "batch_size":  1,
                           "timestamp":  "2026-05-21T08:07:00.191931+00:00"
                       },
    "model_info":  {
                       "input_names":  [
                                           "input_ids",
                                           "attention_mask",
                                           "token_type_ids"
                                       ],
                       "input_shapes":  [
                                            [
                                                1,
                                                512
                                            ],
                                            [
                                                1,
                                                512
                                            ],
                                            [
                                                1,
                                                512
                                            ]
                                        ],
                       "input_types":  [
                                           "int32",
                                           "int32",
                                           "int32"
                                       ],
                       "output_names":  [
                                            "logits"
                                        ],
                       "output_shapes":  [
                                             [
                                                 1,
                                                 512,
                                                 9
                                             ]
                                         ]
                   },
    "latency_ms":  {
                       "mean":  230.46,
                       "min":  225.53,
                       "max":  235.81,
                       "p50":  230.92,
                       "p90":  235.81,
                       "p95":  235.81,
                       "p99":  235.81,
                       "std":  3.86,
                       "warmup_mean":  null
                   },
    "throughput":  {
                       "samples_per_sec":  4.34,
                       "batches_per_sec":  4.34
                   },
    "raw_samples_ms":  [

                       ]
}
