{
  "benchmark_info": {
    "model_id": "nvidia/segformer-b1-finetuned-ade-512-512",
    "task": "image-segmentation",
    "device": "gpu",
    "precision": "auto",
    "iterations": 100,
    "warmup": 10,
    "batch_size": 1,
    "timestamp": "2026-05-18T22:18:29.394998+00:00"
  },
  "model_info": {
    "input_names": [
      "pixel_values"
    ],
    "input_shapes": [
      [
        1,
        3,
        512,
        512
      ]
    ],
    "input_types": [
      "float32"
    ],
    "output_names": [
      "logits"
    ],
    "output_shapes": [
      [
        1,
        150,
        128,
        128
      ]
    ]
  },
  "latency_ms": {
    "mean": 37.53,
    "min": 28.759,
    "max": 62.378,
    "p50": 37.898,
    "p90": 44.397,
    "p95": 44.938,
    "p99": 62.378,
    "std": 6.44,
    "warmup_mean": 31.893
  },
  "throughput": {
    "samples_per_sec": 26.65,
    "batches_per_sec": 26.65
  },
  "raw_samples_ms": [
    32.239,
    31.962,
    30.692,
    32.118,
    32.347,
    33.254,
    32.091,
    32.525,
    31.849,
    32.002,
    33.586,
    32.245,
    30.316,
    29.327,
    29.582,
    32.612,
    30.155,
    29.763,
    29.647,
    31.954,
    32.848,
    32.466,
    32.967,
    33.564,
    29.984,
    29.069,
    28.759,
    29.122,
    29.341,
    30.765,
    30.467,
    30.606,
    30.317,
    30.339,
    29.02,
    30.611,
    31.892,
    34.284,
    31.039,
    30.46,
    29.666,
    43.873,
    34.228,
    33.491,
    31.599,
    32.432,
    33.018,
    32.845,
    35.836,
    37.142,
    37.898,
    38.644,
    38.082,
    38.993,
    37.823,
    39.209,
    38.349,
    40.854,
    43.737,
    44.174,
    43.658,
    43.508,
    43.769,
    43.724,
    44.574,
    44.331,
    44.91,
    42.905,
    42.597,
    44.397,
    43.955,
    41.897,
    42.7,
    43.367,
    43.085,
    42.301,
    42.998,
    43.995,
    43.431,
    44.824,
    44.208,
    44.151,
    47.923,
    44.928,
    44.243,
    40.855,
    42.87,
    43.933,
    45.516,
    42.649,
    43.348,
    41.466,
    43.915,
    44.938,
    45.596,
    41.8,
    62.378,
    43.013,
    43.293,
    41.019
  ]
}