{
  "benchmark_info": {
    "model_id": "Intel/bert-base-uncased-mrpc",
    "task": "text-classification",
    "device": "cpu",
    "precision": "auto",
    "iterations": 100,
    "warmup": 10,
    "batch_size": 1,
    "timestamp": "2026-05-11T22:33:07.415198+00:00"
  },
  "model_info": {
    "input_names": [
      "input_ids",
      "attention_mask",
      "token_type_ids"
    ],
    "input_shapes": [
      [
        1,
        512
      ],
      [
        1,
        512
      ],
      [
        1,
        512
      ]
    ],
    "input_types": [
      "int32",
      "int32",
      "int32"
    ],
    "output_names": [
      "logits"
    ],
    "output_shapes": [
      [
        1,
        2
      ]
    ]
  },
  "latency_ms": {
    "mean": 661.995,
    "min": 466.286,
    "max": 1351.005,
    "p50": 610.913,
    "p90": 890.329,
    "p95": 950.546,
    "p99": 1351.005,
    "std": 162.033,
    "warmup_mean": 512.076
  },
  "throughput": {
    "samples_per_sec": 1.51,
    "batches_per_sec": 1.51
  },
  "raw_samples_ms": [
    583.247,
    757.053,
    1239.227,
    918.653,
    690.084,
    552.22,
    714.565,
    950.546,
    724.136,
    1049.082,
    890.329,
    902.895,
    591.117,
    655.035,
    760.356,
    608.256,
    593.077,
    555.656,
    695.376,
    786.31,
    573.941,
    690.877,
    696.777,
    671.447,
    658.804,
    589.367,
    557.391,
    510.085,
    559.992,
    577.899,
    550.067,
    598.975,
    695.426,
    692.362,
    890.049,
    669.966,
    579.964,
    567.292,
    625.946,
    789.676,
    1351.005,
    703.618,
    636.76,
    635.729,
    497.003,
    548.415,
    584.115,
    600.974,
    561.675,
    574.966,
    678.465,
    617.281,
    693.01,
    539.68,
    543.938,
    506.707,
    620.774,
    910.837,
    631.185,
    762.796,
    707.37,
    479.369,
    531.713,
    593.827,
    655.497,
    534.691,
    514.628,
    466.286,
    522.349,
    534.687,
    591.643,
    710.167,
    651.079,
    673.28,
    634.314,
    566.457,
    716.668,
    814.275,
    800.089,
    856.389,
    571.61,
    548.541,
    567.463,
    511.096,
    535.395,
    495.36,
    610.913,
    655.128,
    1274.472,
    947.808,
    768.269,
    554.385,
    564.48,
    601.079,
    588.87,
    575.025,
    492.685,
    568.759,
    492.709,
    558.228
  ]
}