{
  "benchmark_info": {
    "model_id": "BAAI/bge-base-en-v1.5",
    "task": "sentence-similarity",
    "device": "npu",
    "precision": "auto",
    "iterations": 100,
    "warmup": 10,
    "batch_size": 1,
    "timestamp": "2026-04-28T03:17:38.297092+00:00"
  },
  "model_info": {
    "input_names": [
      "input_ids",
      "attention_mask",
      "token_type_ids"
    ],
    "input_shapes": [
      [
        1,
        512
      ],
      [
        1,
        512
      ],
      [
        1,
        512
      ]
    ],
    "input_types": [
      "int32",
      "int32",
      "int32"
    ],
    "output_names": [
      "last_hidden_state",
      "1341"
    ],
    "output_shapes": [
      [
        1,
        512,
        768
      ],
      [
        1,
        768
      ]
    ]
  },
  "latency_ms": {
    "mean": 53.278,
    "min": 50.919,
    "max": 64.708,
    "p50": 52.167,
    "p90": 56.885,
    "p95": 59.175,
    "p99": 64.708,
    "std": 2.605,
    "warmup_mean": 53.886
  },
  "throughput": {
    "samples_per_sec": 18.77,
    "batches_per_sec": 18.77
  },
  "raw_samples_ms": [
    52.664,
    51.928,
    59.34,
    52.028,
    52.287,
    53.684,
    50.936,
    50.919,
    52.134,
    52.165,
    52.602,
    52.112,
    56.785,
    52.321,
    52.026,
    51.35,
    51.491,
    59.217,
    52.65,
    52.106,
    52.179,
    56.281,
    51.405,
    54.062,
    53.393,
    51.282,
    51.373,
    51.325,
    64.708,
    51.975,
    52.004,
    51.704,
    54.05,
    51.452,
    51.986,
    52.11,
    51.933,
    54.593,
    56.258,
    52.575,
    52.167,
    53.131,
    53.932,
    52.619,
    51.234,
    51.181,
    51.226,
    53.744,
    52.766,
    52.218,
    51.959,
    51.85,
    56.187,
    51.173,
    56.885,
    52.049,
    53.853,
    51.556,
    52.612,
    52.788,
    52.08,
    59.076,
    51.644,
    51.452,
    51.724,
    52.131,
    52.081,
    54.323,
    51.88,
    51.603,
    51.743,
    58.634,
    51.78,
    52.512,
    51.718,
    58.655,
    52.369,
    51.859,
    52.264,
    63.847,
    52.054,
    55.17,
    52.629,
    56.211,
    55.441,
    51.906,
    51.827,
    52.166,
    52.464,
    59.175,
    51.937,
    52.297,
    51.9,
    56.412,
    51.79,
    52.739,
    51.012,
    54.257,
    53.577,
    56.948
  ]
}